monkey/dao/pymongo/dao.py
monkey/dao/pymongo/results.py
monkey_dao_pymongo-2.0.0b2.dist-info/licenses/LICENSE
monkey_dao_pymongo-2.0.0b2.dist-info/METADATA
monkey_dao_pymongo-2.0.0b2.dist-info/WHEEL
monkey_dao_pymongo-2.0.0b2.dist-info/top_level.txt
monkey_dao_pymongo-2.0.0b2.dist-info/RECORD
