Metadata-Version: 2.4
Name: monkey.dao.pymongo
Version: 2.0.0b2
Summary: Simple Data Access Object pattern implementation for MongoDB database.
Author-email: Xavier ROY <xavier@monkey-python.org>
Project-URL: Repository, https://bitbucket.org/monkey-python/monkey-dao-pymongo/
Classifier: Programming Language :: Python
Classifier: Development Status :: 4 - Beta
Classifier: Operating System :: OS Independent
Classifier: Programming Language :: Python :: 3.10
Classifier: Topic :: Software Development :: Libraries :: Python Modules
Classifier: Intended Audience :: Developers
Requires-Python: >=3.10
License-File: LICENSE
Requires-Dist: monkey.dao>=2.0.0b1
Requires-Dist: pymongo>=4.3.3
Requires-Dist: setuptools
Dynamic: license-file
